{
  "stageId": 4,
  "stageEnemyList": [
    {
      "id": 0,
      "level": 0,
      "pos": {
        "x": 2.0,
        "y": -5.0
      },
      "yRotation": 180.0
    },
    {
      "id": 0,
      "level": 0,
      "pos": {
        "x": -2.0,
        "y": 5.0
      },
      "yRotation": 0.0
    },
    {
      "id": 0,
      "level": 0,
      "pos": {
        "x": 2,
        "y": -5.0
      },
      "yRotation": 0.0
    },
    {
      "id": 0,
      "level": 0,
      "pos": {
        "x": -2.0,
        "y": -5.0
      },
      "yRotation": 0.0
    },
    {
      "id": 1,
      "level": 0,
      "pos": {
        "x": 0.0,
        "y": 6.0
      },
      "yRotation": 180.0
    },
    {
      "id": 1,
      "level": 0,
      "pos": {
        "x": 0.0,
        "y": -6.0
      },
      "yRotation": 0.0
    },
    {
      "id": 0,
      "level": 0,
      "pos": {
        "x": -6.0,
        "y": 0.0
      },
      "yRotation": 180.0
    },
    {
      "id": 0,
      "level": 0,
      "pos": {
        "x": 6.0,
        "y": 0.0
      },
      "yRotation": 180.0
    }
  ]
}